py_secureapikeys_azumio/__init__.py
py_secureapikeys_azumio/apikeys.py
py_secureapikeys_azumio-1.0.1.dist-info/LICENSE
py_secureapikeys_azumio-1.0.1.dist-info/METADATA
py_secureapikeys_azumio-1.0.1.dist-info/WHEEL
py_secureapikeys_azumio-1.0.1.dist-info/top_level.txt
py_secureapikeys_azumio-1.0.1.dist-info/RECORD
