Metadata-Version: 2.1
Name: py-secureapikeys-azumio
Version: 1.0.1
Home-page: https://github.com/azumio/secureapikeys
Author: Igor Rendulic
Author-email: Igor Rendulic <igor@azumio.com>
License: 
Project-URL: Homepage, https://github.com/azumio/py-secureapikeys
Project-URL: Bug Tracker, https://github.com/azumio/py-secureapikeys/issues
Classifier: Programming Language :: Python :: 3
Classifier: License :: OSI Approved :: Apache Software License
Classifier: Operating System :: OS Independent
Classifier: Topic :: Security :: Cryptography
Requires-Python: >=3.7
License-File: LICENSE
Requires-Dist: google-cloud-kms (==2.11.0)
Requires-Dist: crcmod
